LICENSE.txt
MANIFEST.in
setup.cfg
setup.py
cr_py/.DS_Store
cr_py/__init__.py
cr_py/core.py
cr_py.egg-info/PKG-INFO
cr_py.egg-info/SOURCES.txt
cr_py.egg-info/dependency_links.txt
cr_py.egg-info/requires.txt
cr_py.egg-info/top_level.txt
cr_py/__pycache__/__init__.cpython-36.pyc
cr_py/__pycache__/core.cpython-36.pyc