Metadata-Version: 1.1
Name: cr-py
Version: 1.1.4
Summary: A Python API wrapper for cr-api
Home-page: https://github.com/kwugfighter/cr.py
Author: kwugfighter
Author-email: isaacli430@gmail.com
License: MIT
Keywords: cr,Clash Royale,CR API
Platform: UNKNOWN
Classifier: Development Status :: 3 - Alpha
Classifier: Intended Audience :: Developers
Classifier: Topic :: Software Development :: Build Tools
Classifier: License :: OSI Approved :: MIT License
Classifier: Programming Language :: Python :: 3
Classifier: Programming Language :: Python :: 3.3
Classifier: Programming Language :: Python :: 3.4
Classifier: Programming Language :: Python :: 3.5
Classifier: Programming Language :: Python :: 3.6
